ghtoken/__init__.py
ghtoken/__main__.py
ghtoken/py.typed
ghtoken-0.1.1.dist-info/METADATA
ghtoken-0.1.1.dist-info/WHEEL
ghtoken-0.1.1.dist-info/entry_points.txt
ghtoken-0.1.1.dist-info/licenses/LICENSE
ghtoken-0.1.1.dist-info/RECORD
