Metadata-Version: 2.3
Name: ghtoken
Version: 0.1.1
Summary: Retrieve GitHub access tokens from various sources
Project-URL: Source Code, https://github.com/jwodder/ghtoken
Project-URL: Bug Tracker, https://github.com/jwodder/ghtoken/issues
Author-email: John Thorvald Wodder II <ghtoken@varonathe.org>
License-Expression: MIT
License-File: LICENSE
Keywords: GH_TOKEN,GitHub,GitHub API,GitHub token
Classifier: Intended Audience :: Developers
Classifier: License :: OSI Approved :: MIT License
Classifier: Programming Language :: Python :: 3
Classifier: Programming Language :: Python :: 3 :: Only
Classifier: Programming Language :: Python :: 3.8
Classifier: Programming Language :: Python :: 3.9
Classifier: Programming Language :: Python :: 3.10
Classifier: Programming Language :: Python :: 3.11
Classifier: Programming Language :: Python :: 3.12
Classifier: Programming Language :: Python :: Implementation :: CPython
Classifier: Programming Language :: Python :: Implementation :: PyPy
Classifier: Topic :: Internet :: WWW/HTTP
Classifier: Topic :: Software Development
Classifier: Topic :: Software Development :: Version Control :: Git
Classifier: Topic :: Utilities
Classifier: Typing :: Typed
Requires-Python: >=3.8
Requires-Dist: python-dotenv<2.0,>=0.11
Requires-Dist: ruamel-yaml<1.0,>=0.15
